{
  "name": "Harriet Jackson",
  "age": 45,
  "address": {
    "street": "Siftur Drive",
    "city": "Duehba",
    "state": "SC",
    "zip": "14963"
  },
  "contact": {
    "phone": "(988) 629-3271",
    "servicePhone": "800979744"
  },
  "birthday": "1976-03-18T15:57:03.101Z",
  "ip": "131.117.119.163",
  "foo": "bar",
  "profile": {
    "about": "Zafke usev memojaso azciv demkinew id haeha ujsuhil miko ga ne fimtogtut ibugovip kew usokuk mo liote. Gettizap otkeja cozodheb ruere jemsah kal avehezi gi ojo en famik lu vefne mum nezgi. Talog maker sozwawi bi muplih mujtuaz tiggibuj otakezez si ogwe zuizpo tuv ovedev savjo kib hof ug mopagec. Tucica sivgavben po finom hekmi pe rohtuho volgo badi jevuk howga hatlafug kagogku igugir. Dih wamem zerluji pelnuwif liodwi kasehzom sav geg imiec lipu tumli seebjup siab hedkutde wumuzwap.",
    "bio": "Jofit renev wovedbu cuc vudewpe po ki afbu falisu bepfu keh pu hejbidafo zu begdi ukaru vi mif. Saebe hog loinuvu govowiah ihu jo neloh ukavooci dup sap gowowa wekhep ef jomerudaj tukuzpu ase dujraopu. Palowle jogboari ti vud loukbik dose uvema hu afi tep la goguwbi."
  },
  "apiKey": "159278439ebe09792c9cd5479df19918728fac72b959c39609d45fb200a23190",
  "currency": {
    "code": "LSL",
    "name": "Lesotho Loti"
  }
}